apriori/__init__.py
apriori/apriori.py
apriori/apriori_types.py
apriori/gh_ap.py
apriori/rule.py
apriori/transaction.py
kiwi_apriori-0.3.2.dist-info/METADATA
kiwi_apriori-0.3.2.dist-info/WHEEL
kiwi_apriori-0.3.2.dist-info/top_level.txt
kiwi_apriori-0.3.2.dist-info/RECORD
