Metadata-Version: 2.1
Name: kiwi-apriori
Version: 0.3.2
Summary: Association Analysis Package
Home-page: https://github.com/kiwidamien/apriori
Author: Damien Martin
License: MIT
Platform: UNKNOWN
Classifier: License :: OSI Approved :: MIT License
Classifier: Programming Language :: Python
Classifier: Programming Language :: Python :: 3
Classifier: Programming Language :: Python :: 3.6
Classifier: Programming Language :: Python :: Implementation :: CPython
Classifier: Programming Language :: Python :: Implementation :: PyPy
Requires-Python: >=3.6.0
Requires-Dist: pydantic
Provides-Extra: tests
Requires-Dist: pytest ; extra == 'tests'
